iithlp/__init__.py
iithlp/core.py
iithlp/data/mappings/bengali.json
iithlp/data/mappings/devanagari.json
iithlp/data/mappings/gujarati.json
iithlp/data/mappings/gurmukhi.json
iithlp/data/mappings/kannada.json
iithlp/data/mappings/malayalam.json
iithlp/data/mappings/odia.json
iithlp/data/mappings/tamil.json
iithlp/data/mappings/telugu.json
iithlp-0.2.5.dist-info/licenses/LICENSE
iithlp-0.2.5.dist-info/METADATA
iithlp-0.2.5.dist-info/WHEEL
iithlp-0.2.5.dist-info/top_level.txt
iithlp-0.2.5.dist-info/RECORD
