Metadata-Version: 2.4
Name: iithlp
Version: 0.2.5
Summary: A comprehensive transliteration scheme for Indian languages
Home-page: https://github.com/theAutoBiography/iithlp
Author: Ramanan S
Author-email: ramanan93@gmail.com
Classifier: Programming Language :: Python :: 3
Classifier: License :: OSI Approved :: MIT License
Classifier: Operating System :: OS Independent
Requires-Python: >=3.6
License-File: LICENSE
Dynamic: author
Dynamic: author-email
Dynamic: classifier
Dynamic: description
Dynamic: description-content-type
Dynamic: home-page
Dynamic: license-file
Dynamic: requires-python
Dynamic: summary
